IPYNBrender/__init__.py
IPYNBrender/custom_exception.py
IPYNBrender/logger.py
IPYNBrender/youtube.py
IPYNBrenderer/__init__.py
IPYNBrender-0.0.4.dist-info/LICENSE
IPYNBrender-0.0.4.dist-info/METADATA
IPYNBrender-0.0.4.dist-info/WHEEL
IPYNBrender-0.0.4.dist-info/top_level.txt
IPYNBrender-0.0.4.dist-info/RECORD
